setup.py
src/FlexSeleniumLibrary/__init__.py
src/FlexSeleniumLibrary/flexpilotcommands.py
src/FlexSeleniumLibrary/sfapicommands.py
src/FlexSeleniumLibrary/keywords/__init__.py
src/FlexSeleniumLibrary/keywords/flexpilot_keywords.py
src/FlexSeleniumLibrary/keywords/flexselenium_keywords.py
src/robotframework_flexseleniumlibrary.egg-info/PKG-INFO
src/robotframework_flexseleniumlibrary.egg-info/SOURCES.txt
src/robotframework_flexseleniumlibrary.egg-info/dependency_links.txt
src/robotframework_flexseleniumlibrary.egg-info/requires.txt
src/robotframework_flexseleniumlibrary.egg-info/top_level.txt