Metadata-Version: 1.0
Name: robotframework-flexseleniumlibrary
Version: 0.3.0
Summary: Adobe Flex testing library for Robot Framework
Home-page: https://github.com/hirsivaja/FlexSeleniumLibrary
Author: Toni Lappalainen
Author-email: <hirsivaja@users.noreply.github.com>
License: Apache License 2.0
Keywords: robotframework testing testautomation selenium webdriver flex FlexPilot SeleniumFlexAPI
Platform: any
